advanced_navigation/__init__.py
advanced_navigation/an_devices/__init__.py
advanced_navigation/an_devices/advanced_navigation_device_serial.py
advanced_navigation/an_devices/advanced_navigation_device_tcp.py
advanced_navigation/an_devices/air_data_unit_device.py
advanced_navigation/an_devices/boreas_device.py
advanced_navigation/an_devices/certus_device.py
advanced_navigation/an_devices/certus_evo_device.py
advanced_navigation/an_devices/gnss_compass_device.py
advanced_navigation/an_devices/motus_device.py
advanced_navigation/an_devices/orientus_device.py
advanced_navigation/an_devices/spatial_device.py
advanced_navigation/an_devices/spatial_dual_device.py
advanced_navigation/an_devices/spatial_fog_device.py
advanced_navigation/an_devices/spatial_fog_dual_device.py
advanced_navigation/anpp_packets/__init__.py
advanced_navigation/anpp_packets/an_packet_0.py
advanced_navigation/anpp_packets/an_packet_1.py
advanced_navigation/anpp_packets/an_packet_10.py
advanced_navigation/anpp_packets/an_packet_11.py
advanced_navigation/anpp_packets/an_packet_13.py
advanced_navigation/anpp_packets/an_packet_14.py
advanced_navigation/anpp_packets/an_packet_180.py
advanced_navigation/anpp_packets/an_packet_181.py
advanced_navigation/anpp_packets/an_packet_182.py
advanced_navigation/anpp_packets/an_packet_184.py
advanced_navigation/anpp_packets/an_packet_185.py
advanced_navigation/anpp_packets/an_packet_186.py
advanced_navigation/anpp_packets/an_packet_188.py
advanced_navigation/anpp_packets/an_packet_189.py
advanced_navigation/anpp_packets/an_packet_190.py
advanced_navigation/anpp_packets/an_packet_191.py
advanced_navigation/anpp_packets/an_packet_192.py
advanced_navigation/anpp_packets/an_packet_193.py
advanced_navigation/anpp_packets/an_packet_194.py
advanced_navigation/anpp_packets/an_packet_195.py
advanced_navigation/anpp_packets/an_packet_196.py
advanced_navigation/anpp_packets/an_packet_197.py
advanced_navigation/anpp_packets/an_packet_198.py
advanced_navigation-0.1.74.dist-info/LICENSE.txt
advanced_navigation-0.1.74.dist-info/METADATA
advanced_navigation-0.1.74.dist-info/WHEEL
advanced_navigation-0.1.74.dist-info/RECORD
