Metadata-Version: 2.1
Name: advanced_navigation
Version: 0.1.74
Summary: 
Author: Charles Balderstone
Author-email: charles.balderstone@advancednavigation.com
Requires-Python: >=3.10,<4.0
Classifier: Programming Language :: Python :: 3
Classifier: Programming Language :: Python :: 3.10
Classifier: Programming Language :: Python :: 3.11
Classifier: Programming Language :: Python :: 3.12
Requires-Dist: fastcrc (>=0.3.0,<0.4.0)
Requires-Dist: pyserial (>=3.5.0,<4.0.0)
